rtl/fifo.sv
module fifo (
    input [31:0] data_in,
    input push,
    pop,
    clk,
    reset,
    output logic [31:0] data_out,
    output bit empty,
    full
);
  reg [3:0] index_push;
  reg [3:0] index_pop;
  logic [2:0] count;
  logic [31:0] fifo_reg[0:6];
  always @(posedge clk or negedge reset) begin
    if (~reset) begin
      foreach (fifo_reg[i]) fifo_reg[i] = 32'b0;
      index_push = 4'b0;
      index_pop = 4'b0;
      count = 3'd0;
      full = 1'b0;
      empty = 1'b1;
    end else begin
      if (push) begin
        if (index_push == 3'd7) index_push = 3'd0;
        if (count < 3'd7) begin
          fifo_reg[index_push] = data_in;
          index_push = index_push + 3'b1;
          count++;
          full  = 1'b0;
          empty = 1'b0;
        end
        if (count == 3'd7) begin
          full  = 1'b1;
          //           if (index_push >= 6) index_push = 0;
          empty = 1'b0;
        end
      end
      if (pop) begin
        if (index_pop == 3'd7) index_pop = 3'd0;
        if (count != 4'b0) begin
          data_out = fifo_reg[index_pop];
          fifo_reg[index_pop] = 32'b0;
          index_pop = index_pop + 3'b1;
          count--;
          empty = 1'b0;
          full  = 1'b0;
        end
      end
      if (count == 0) begin
        full  = 1'b0;
        //         if (index_pop >= 6) index_pop = 0;
        empty = 1'b1;
      end
    end
  end
endmodule

tb/sv_tb.sv
class data;
  randc logic [31:0] data_in;
  rand logic push;
  rand logic pop;
  bit full;
  bit empty;

  int i = 0;
  int j = 0;
  int count = 0;
  logic [31:0] data_reg[0:6];
  logic [31:0] data_out;

  constraint c_push_pop {
    if (push) pop != 1;
    if (pop) push != 1;
  }
  constraint c_full_empty {
    if (full) push != 1;
    if (empty) pop != 1;
  }

  function void post_randomize();
    $display("time %t data_in:%h pop:%d push:%d", $time, data_in, pop, push);
    if (count == 7) begin
      full  = 1;
      empty = 0;
    end
    if (count == 0) begin
      empty = 1;
      full  = 0;
    end

    if (push) begin
      if (i >= 7) i = 0;
      if (count < 7) begin
        data_reg[i] = data_in;
        i = i + 1;
        count++;
        empty = 0;
      end
    end
    if (pop) begin
      if (j >= 7) j = 0;
      if (count > 0) begin
        data_out = data_reg[j];
        j = j + 1;
        count--;
        full = 0;
      end
    end


  endfunction
endclass

module tb ();
  logic [31:0] data_in;
  logic push, pop, clk, reset;
  logic [31:0] data_out;
  logic [31:0] form_data_pkt_out, form_dut_data_out;
  bit empty, full;
  data d1;

  fifo f1 (
      .data_in(data_in),
      .push(push),
      .pop(pop),
      .clk(clk),
      .reset(reset),
      .data_out(data_out),
      .empty(empty),
      .full(full)
  );

  initial begin
    $dumpfile("dump.vcd");
    $dumpvars(0, tb);
    d1 = new();
    #0 clk = 0;
    reset = 0;
    #1 clk = 0;
    reset = 1;
    #500 $finish;
  end
  always #5 clk = ~clk;
  always @(posedge clk) begin
    d1.randomize();
    data_in = d1.data_in;
    push = d1.push;
    pop = d1.pop;

  end


  always @(posedge clk) begin
    $display("time: %t", $time);
    foreach (f1.fifo_reg[i]) $display("fifo[%d]: %h", i, f1.fifo_reg[i]);
  end
  always @(posedge clk) begin
    if (pop) begin

      @(posedge clk);
      #1;
      form_data_pkt_out <= d1.data_out;
      form_dut_data_out <= data_out;
      if (d1.data_out == data_out) $display("pass");
      else
        $display(
            "j=%d d1.data_out=%h   index_pop=%d data_out=%h",
            d1.j,
            d1.data_out,
            f1.index_pop,
            data_out
        );
    end
  end
endmodule

dump.vcd
$date
	Thu May 28 05:40:18 2026
$end
$version
	QuestaSim Version 2025.2
$end
$timescale
	1ns
$end

$scope module tb $end
$var reg 1 ! clk $end
$var reg 32 " data_in [31:0] $end
$var reg 32 # data_out [31:0] $end
$var reg 32 $ form_data_pkt_out [31:0] $end
$var reg 32 % form_dut_data_out [31:0] $end
$var reg 1 & pop $end
$var reg 1 ' push $end
$var reg 1 ( reset $end
$var reg 1 ) empty $end
$var reg 1 * full $end

$scope module f1 $end
$var wire 1 + clk $end
$var wire 1 , data_in [31] $end
$var wire 1 - data_in [30] $end
$var wire 1 . data_in [29] $end
$var wire 1 / data_in [28] $end
$var wire 1 0 data_in [27] $end
$var wire 1 1 data_in [26] $end
$var wire 1 2 data_in [25] $end
$var wire 1 3 data_in [24] $end
$var wire 1 4 data_in [23] $end
$var wire 1 5 data_in [22] $end
$var wire 1 6 data_in [21] $end
$var wire 1 7 data_in [20] $end
$var wire 1 8 data_in [19] $end
$var wire 1 9 data_in [18] $end
$var wire 1 : data_in [17] $end
$var wire 1 ; data_in [16] $end
$var wire 1 < data_in [15] $end
$var wire 1 = data_in [14] $end
$var wire 1 > data_in [13] $end
$var wire 1 ? data_in [12] $end
$var wire 1 @ data_in [11] $end
$var wire 1 A data_in [10] $end
$var wire 1 B data_in [9] $end
$var wire 1 C data_in [8] $end
$var wire 1 D data_in [7] $end
$var wire 1 E data_in [6] $end
$var wire 1 F data_in [5] $end
$var wire 1 G data_in [4] $end
$var wire 1 H data_in [3] $end
$var wire 1 I data_in [2] $end
$var wire 1 J data_in [1] $end
$var wire 1 K data_in [0] $end
$var wire 1 L pop $end
$var wire 1 M push $end
$var wire 1 N reset $end
$var reg 3 O count [2:0] $end
$var reg 32 P data_out [31:0] $end
$var reg 4 Q index_pop [3:0] $end
$var reg 4 R index_push [3:0] $end
$var reg 1 S empty $end
$var reg 1 T full $end
$upscope $end
$upscope $end
$enddefinitions $end
#0
$dumpvars
0N
0+
xL
xM
xK
xJ
xI
xH
xG
xF
xE
xD
xC
xB
xA
x@
x?
x>
x=
x<
x;
x:
x9
x8
x7
x6
x5
x4
x3
x2
x1
x0
x/
x.
x-
x,
0!
bx "
bx #
bx $
bx %
x&
x'
0(
1)
0*
b0 O
bx P
b0 Q
b0 R
1S
0T
$end
#1
1(
1N
#5
1!
1+
b111100001001001000100001110 "
1'
0&
0K
1J
1I
1H
0G
0F
0E
0D
1C
0B
0A
0@
1?
0>
0=
1<
0;
0:
19
08
07
06
05
14
13
12
11
00
0/
0.
0-
0,
1M
0L
#10
0!
0+
#15
1!
1+
b1 R
b1 O
0S
b101100101101010011000110011101 "
0)
1K
0J
1G
1D
1>
0<
1;
17
16
03
02
10
1.
#20
0!
0+
#25
1!
1+
b10 R
b10 O
b10001010101000000110001100010100 "
0'
0K
0H
0D
1B
0?
1=
0;
09
07
12
01
0.
1,
0M
#30
0!
0+
#35
1!
1+
b11101011001001111100111100110011 "
1'
1K
1J
0I
1F
1A
1@
0>
1<
1;
1:
19
04
13
1.
1-
1M
#40
0!
0+
#45
1!
1+
b11 R
b11 O
b11011101000100001110100110111010 "
0'
0K
1H
1D
0B
0A
1>
0;
0:
09
17
06
02
11
1/
0.
0M
#50
0!
0+
#55
1!
1+
b1010000011011001110000001101001 "
1'
1K
0J
0G
1E
0D
0C
0@
19
18
07
16
15
03
01
00
0,
1M
#60
0!
0+
#65
1!
1+
b100 R
b100 O
b1000000011101110000101100000000 "
0'
1&
0K
0H
0F
0E
1C
1B
1@
0>
0=
0<
1;
1:
08
17
0/
0M
1L
#70
0!
0+
#75
1!
1+
b111100001001001000100001110 P
b1 Q
b11 O
b11000011010001011101101100111111 "
0&
b111100001001001000100001110 #
1K
1J
1I
1H
1G
1F
1?
1=
1<
0:
07
06
13
12
1,
0L
#76
b111100001001001000100001110 $
b111100001001001000100001110 %
#80
0!
0+
#85
1!
1+
b10111110010010100100110011100110 "
1'
0K
0H
0G
1E
1D
0C
0B
1A
0?
0<
0;
1:
09
18
03
11
10
1/
1.
0-
1M
#90
0!
0+
#95
1!
1+
b101 R
b100 O
b11010100001110011101010110110101 "
1K
0J
1G
0E
1C
0@
1?
1<
1;
0:
17
16
05
02
00
0.
1-
#100
0!
0+
#105
1!
1+
b110 R
b101 O
b11001101100111101101010101101100 "
0'
0K
1H
0G
1E
0D
0;
1:
19
06
14
13
10
0/
0M
#110
0!
0+
#115
1!
1+
b1101000111010111000010111001011 "
1K
1J
0I
0F
1D
0?
0=
1;
09
07
16
15
03
01
1.
0,
#120
0!
0+
#125
1!
1+
b10010001100010110110101010010010 "
0K
0H
1G
0E
0C
1B
0A
1@
1>
1=
0<
06
05
13
00
1/
0.
0-
1,
#130
0!
0+
#135
1!
1+
b10011111000011110100000110000001 "
1'
1K
0J
0G
1C
0B
0@
0>
19
04
12
11
10
1M
#140
0!
0+
#145
1!
1+
b111 R
b110 O
b1010110001011110111001001011000 "
0'
1&
0K
1H
1G
1E
0D
0C
1B
1?
1>
16
03
00
1-
0,
0M
1L
#150
0!
0+
#155
1!
1+
b101100101101010011000110011101 P
b10 Q
b101 O
b10011101000000001111111011010111 "
b101100101101010011000110011101 #
1K
1J
1I
0H
1D
1A
1@
1<
0;
0:
09
08
06
13
02
10
0-
1,
#156
b11101011001001111100111100110011 $
b101100101101010011000110011101 %
#160
0!
0+
#165
1!
1+
b11101011001001111100111100110011 P
b11 Q
b100 O
b10010010010110001111001010111110 "
1'
0&
b11101011001001111100111100110011 #
0K
1H
1F
0E
0A
0@
18
17
15
03
12
01
00
1M
0L
#170
0!
0+
#175
1!
1+
b1 R
b101 O
b100101111110100101001111001101 "
0'
1K
0J
0G
0F
1E
1C
0>
0<
1:
16
14
13
02
11
0/
1.
0,
0M
#180
0!
0+
#185
1!
1+
b1010011110010101001000111000100 "
1&
0K
0H
0B
0=
1<
07
06
12
01
1/
0.
1-
1L
#190
0!
0+
#195
1!
1+
b1010000011011001110000001101001 P
b100 Q
b100 O
b1100111111010000111011001100011 "
1'
0&
b1010000011011001110000001101001 #
1K
1J
0I
1F
0D
0C
1B
1A
1>
1=
0<
0:
16
11
0/
1.
1M
0L
#196
b1010000011011001110000001101001 $
b1010000011011001110000001101001 %
#200
0!
0+
#205
1!
1+
b10 R
b101 O
b10011100001000011001010101101010 "
0K
1H
1C
0B
0>
0=
1<
1;
08
05
04
03
02
10
1/
0.
0-
1,
#210
0!
0+
#215
1!
1+
b11 R
b110 O
b11000111000100011110010011001 "
0'
1&
1K
0J
1G
0F
0E
1D
0C
1@
1>
0<
0;
1:
15
14
01
0,
0M
1L
#220
0!
0+
#225
1!
1+
b10111110010010100100110011100110 P
b101 Q
b101 O
b11010100010110111110001110110000 "
1'
0&
b10111110010010100100110011100110 #
0K
0H
1F
1C
1B
0A
0@
0?
1=
1<
1;
18
17
06
04
11
00
1-
1,
1M
0L
#226
b10111110010010100100110011100110 $
b10111110010010100100110011100110 %
#230
0!
0+
#235
1!
1+
b100 R
b110 O
b10011010001111100001110001101111 "
0'
1K
1J
1I
1H
0G
1E
0D
0C
0B
1A
1@
1?
0>
0=
0<
0;
19
16
05
12
01
10
0-
0M
#240
0!
0+
#245
1!
1+
b11100111111100000001010010110 "
1'
0K
0H
1G
0F
0E
1D
1B
0A
0@
0?
15
14
02
11
0,
1M
#250
0!
0+
#255
1!
1+
b101 R
b111 O
1T
b1110111010010000010101111100101 "
0'
1*
1K
0J
0G
1F
1E
1C
1@
1>
0:
09
07
06
04
13
12
00
1.
1-
0M
#260
0!
0+
#265
1!
1+
b11100000110110010001100000011100 "
0K
1H
1G
0F
0E
0D
0C
0B
1?
0>
1;
17
14
03
02
01
0/
1,
#270
0!
0+
#275
1!
1+
b110101100110000010000011111011 "
1&
1K
1J
0I
1F
1E
1D
0@
0?
1>
0;
05
13
11
1/
0-
0,
1L
#280
0!
0+
#285
1!
1+
b11010100001110011101010110110101 P
b110 Q
b110 O
0T
b10110000011100001110101001000010 "
0&
0*
b11010100001110011101010110110101 #
0K
0H
0G
0F
0D
1B
1@
1=
1<
08
16
15
04
03
01
1,
0L
#286
b11010100001110011101010110110101 $
b11010100001110011101010110110101 %
#290
0!
0+
#295
1!
1+
b1101000001110101000110110001 "
1K
0J
1G
1F
0E
1D
1C
0B
0@
1?
0>
0<
1;
1:
19
07
06
05
13
11
10
0/
0.
0,
#300
0!
0+
#305
1!
1+
b1100000000011101111100001000 "
1&
0K
1H
0G
0F
0D
1B
1A
1@
1<
0:
09
03
1L
#310
0!
0+
#315
1!
1+
b10011111000011110100000110000001 P
b111 Q
b101 O
b10111101010001101011010000000111 "
0&
b10011111000011110100000110000001 #
1K
1J
1I
0H
0C
0B
0@
1>
0=
0;
1:
19
15
13
1/
1.
1,
0L
#316
b10011111000011110100000110000001 $
b10011111000011110100000110000001 %
#320
0!
0+
#325
1!
1+
b1100010001001101111110001101110 "
1&
0K
1H
1F
1E
1@
1=
16
05
03
12
01
00
0/
1-
0,
1L
#330
0!
0+
#335
1!
1+
b1 Q
b10010010010110001111001010111110 P
b100 O
b1010111000101001101110111111101 "
0&
b10010010010110001111001010111110 #
1K
0J
1G
1D
1C
0>
0:
17
06
13
11
1/
0.
0L
#336
b10010010010110001111001010111110 $
b10010010010110001111001010111110 %
#340
0!
0+
#345
1!
1+
b101001000111111110100001110100 "
0K
0H
0D
0C
0A
0?
1>
1;
1:
18
02
01
10
0/
1.
0-
#350
0!
0+
#355
1!
1+
b1101111000101000000010110010011 "
1&
1K
1J
0I
0F
0E
1D
1C
1A
0@
0>
0=
0<
0;
0:
08
12
11
1-
1L
#360
0!
0+
#365
1!
1+
b1100111111010000111011001100011 P
b10 Q
b11 O
b10011000101101101110100100011010 "
0&
b1100111111010000111011001100011 #
0K
1H
0D
0A
1@
1>
1=
1<
1:
16
14
03
02
01
1/
0.
0-
1,
0L
#366
b1100111111010000111011001100011 $
b1100111111010000111011001100011 %
#370
0!
0+
#375
1!
1+
b11010000010000000000000011001001 "
1&
1K
0J
0G
1E
1D
0C
0@
0>
0=
0<
0:
09
07
06
15
04
00
1-
1L
#380
0!
0+
#385
1!
1+
b10011100001000011001010101101010 P
b11 Q
b10 O
b101010110001101110010001100000 "
0&
b10011100001000011001010101101010 #
0K
0H
1F
0D
1A
1>
1=
1<
1:
19
14
12
10
0/
1.
0-
0,
0L
#386
b10011100001000011001010101101010 $
b10011100001000011001010101101010 %
#390
0!
0+
#395
1!
1+
b1100100000001000100010110011111 "
1&
1K
1J
1I
1H
1G
0F
0E
1D
1C
0>
0<
0:
05
04
02
11
00
1-
1L
#400
0!
0+
#405
1!
1+
b11010100010110111110001110110000 P
b100 Q
b1 O
b10101000011000010110000001000110 "
b11010100010110111110001110110000 #
0K
0H
0G
1E
0D
0C
0A
1>
1;
09
16
15
01
10
0-
1,
#406
b11100111111100000001010010110 $
b11010100010110111110001110110000 %
#410
0!
0+
#415
1!
1+
b11100111111100000001010010110 P
b101 Q
b0 O
1S
b10100101111100011110101000010101 "
1)
b11100111111100000001010010110 #
1K
0J
1G
0E
1B
1@
1<
17
14
13
11
00
#420
0!
0+
#425
1!
1+
b101001100101001000001011001100 "
1'
0&
0K
1H
0G
1E
1D
0@
0>
0=
0;
19
06
05
01
10
0,
1M
0L
#426
b11100111111100000001010010110 %
#430
0!
0+
#435
1!
1+
b110 R
b1 O
0S
b10011001000101011010010000101011 "
0'
0)
1K
1J
0I
1F
0E
0D
0B
1A
1>
1;
04
1/
0.
1,
0M
#440
0!
0+
#445
1!
1+
b1101110100010001000111110010 "
1'
0K
0H
1G
1E
1D
1C
0A
1?
0>
0<
09
15
14
11
0/
0,
1M
#450
0!
0+
#455
1!
1+
b111 R
b10 O
b11010100111011011100100111100001 "
0'
1&
1K
0J
0G
1@
0?
1=
1<
19
18
07
16
03
00
1/
1-
1,
0M
1L
#460
0!
0+
#465
1!
1+
b101001100101001000001011001100 P
b110 Q
b1 O
b10010010111100000111001110111000 "
1'
0&
b101001100101001000001011001100 #
0K
1H
1G
0E
1B
0@
1?
1>
0<
0;
09
08
17
12
01
0-
1M
0L
#466
b101001100101001000001011001100 $
b101001100101001000001011001100 %
#470
0!
0+
#475
1!
1+
b1 R
b10 O
b11100000000000000101000100110111 "
0'
1K
1J
1I
0H
0D
0B
0>
07
06
05
04
02
0/
1.
1-
0M
#480
0!
0+
#485
1!
1+
b1010000110110101010111000011110 "
1&
0K
1H
0F
0C
1B
1A
1@
0?
1>
0=
1<
1:
18
17
15
14
1/
0.
0,
1L
#490
0!
0+
#495
1!
1+
b1101110100010001000111110010 P
b111 Q
b1 O
b10101110000100001101000000101101 "
0&
b1101110100010001000111110010 #
1K
0J
0G
1F
0B
0A
0@
1?
0>
1=
0:
08
05
04
12
11
10
0/
1.
0-
1,
0L
#496
b1101110100010001000111110010 $
b1101110100010001000111110010 %
